TP_OOB_Interaction/__init__.py
TP_OOB_Interaction-2024.10.1.dist-info/LICENSE
TP_OOB_Interaction-2024.10.1.dist-info/METADATA
TP_OOB_Interaction-2024.10.1.dist-info/WHEEL
TP_OOB_Interaction-2024.10.1.dist-info/entry_points.txt
TP_OOB_Interaction-2024.10.1.dist-info/top_level.txt
TP_OOB_Interaction-2024.10.1.dist-info/RECORD
