Metadata-Version: 2.1
Name: TP-OOB-Interaction
Version: 2024.10.1
Summary: Get OOB interactions from Interactsh and send to Discord, Telegram, Slack
Home-page: https://github.com/truocphan/TP-OOB-Interaction
Author: TP Cyber Security
Author-email: tpcybersec2023@gmail.com
License: MIT
Classifier: Programming Language :: Python :: 3
License-File: LICENSE
Requires-Dist: certifi >=2024.8.30
Requires-Dist: cffi >=1.17.1
Requires-Dist: charset-normalizer >=3.3.2
Requires-Dist: cryptography >=43.0.1
Requires-Dist: idna >=3.10
Requires-Dist: json-duplicate-keys >=2024.7.17
Requires-Dist: pycparser >=2.22
Requires-Dist: requests >=2.32.3
Requires-Dist: TP-sendNotify >=2024.9.1
Requires-Dist: urllib3 >=2.2.3
